{"cameraMode":{"drawMode":0,"name":"Shaded","section":"Shading Mode"},"sceneLighting":false,"audioPlay":false,"sceneViewState":{"m_AlwaysRefresh":false,"showFog":true,"showSkybox":true,"showFlares":true,"showImageEffects":true,"showParticleSystems":true,"showVisualEffectGraphs":true,"m_FxEnabled":true},"in2DMode":false,"pivot":{"x":-76.06793212890625,"y":-10.447132110595704,"z":-5.9293975830078129},"rotation":{"x":-0.3660251200199127,"y":-0.6137849688529968,"z":0.3848690688610077,"w":-0.5844500660896301},"size":30.762542724609376,"orthographic":false}